lingress/__init__.py
lingress/lingress.py
lingress/peak_picking.py
lingress/specova.py
lingress/ui_pickie_peak.py
lingress/utility.py
lingress-3.0.8.dist-info/licenses/LICENSE
lingress-3.0.8.dist-info/METADATA
lingress-3.0.8.dist-info/WHEEL
lingress-3.0.8.dist-info/top_level.txt
lingress-3.0.8.dist-info/RECORD
