Metadata-Version: 2.4
Name: lingress
Version: 3.0.8
Summary: Metabolomics data analysis with univariate (linear regression) and visualization tools.
Home-page: https://github.com/aeiwz/lingress.git
Download-URL: https://github.com/aeiwz/lingress/archive/refs/tags/v3.0.8.tar.gz
Author: aeiwz
Author-email: theerayut_aeiw_123@hotmail.com
License: MIT
Keywords: Omics,Chemometrics,Visualization,Data Analysis,Univariate,Linear Regression
Classifier: Development Status :: 3 - Alpha
Classifier: Intended Audience :: Education
Classifier: Topic :: Software Development :: Build Tools
Classifier: License :: OSI Approved :: MIT License
Classifier: Programming Language :: Python :: 3.11
License-File: LICENSE
Requires-Dist: scikit-learn
Requires-Dist: pandas
Requires-Dist: numpy
Requires-Dist: matplotlib
Requires-Dist: seaborn
Requires-Dist: scipy
Requires-Dist: statsmodels
Requires-Dist: plotly
Requires-Dist: dash
Requires-Dist: dash_bootstrap_components
Requires-Dist: pyChemometrics
Dynamic: author
Dynamic: author-email
Dynamic: classifier
Dynamic: description
Dynamic: download-url
Dynamic: home-page
Dynamic: keywords
Dynamic: license
Dynamic: license-file
Dynamic: requires-dist
Dynamic: summary
